oasis_data_manager/__init__.py
oasis_data_manager/config.py
oasis_data_manager/complex/__init__.py
oasis_data_manager/complex/complex.py
oasis_data_manager/complex/examples.py
oasis_data_manager/df_reader/__init__.py
oasis_data_manager/df_reader/config.py
oasis_data_manager/df_reader/exceptions.py
oasis_data_manager/df_reader/reader.py
oasis_data_manager/df_reader/backends/__init__.py
oasis_data_manager/df_reader/backends/base.py
oasis_data_manager/df_reader/backends/dask.py
oasis_data_manager/df_reader/backends/pandas.py
oasis_data_manager/df_reader/backends/pyarrow.py
oasis_data_manager/errors/__init__.py
oasis_data_manager/filestore/__init__.py
oasis_data_manager/filestore/config.py
oasis_data_manager/filestore/filestore.py
oasis_data_manager/filestore/log.py
oasis_data_manager/filestore/backends/__init__.py
oasis_data_manager/filestore/backends/aws_s3.py
oasis_data_manager/filestore/backends/azure_abfs.py
oasis_data_manager/filestore/backends/base.py
oasis_data_manager/filestore/backends/local.py
oasis_data_manager-0.1.6.dist-info/METADATA
oasis_data_manager-0.1.6.dist-info/WHEEL
oasis_data_manager-0.1.6.dist-info/top_level.txt
oasis_data_manager-0.1.6.dist-info/RECORD
