Metadata-Version: 2.1
Name: oasis-data-manager
Version: 0.1.6
Summary: UNKNOWN
Home-page: https://github.com/OasisLMF/OasisDataManager
Author: Oasis LMF
Author-email: support@oasislmf.org
License: UNKNOWN
Platform: UNKNOWN
Classifier: Development Status :: 4 - Beta
Classifier: Operating System :: OS Independent
Classifier: Programming Language :: Python
Classifier: Programming Language :: Python :: 3.6
Requires-Python: >=3.6
Requires-Dist: fastparquet
Requires-Dist: fsspec>=2023.12.2
Requires-Dist: pandas
Requires-Dist: typing-extensions
Provides-Extra: extra
Requires-Dist: adlfs; extra == "extra"
Requires-Dist: boto3; extra == "extra"
Requires-Dist: dask>2024.1.1; extra == "extra"
Requires-Dist: dask-geopandas; extra == "extra"
Requires-Dist: dask-sql; extra == "extra"
Requires-Dist: distributed; extra == "extra"
Requires-Dist: geopandas==0.14.4; extra == "extra"
Requires-Dist: pyogrio; extra == "extra"
Requires-Dist: s3fs>=2023.12.2; extra == "extra"
